veriphi_core-0.1.3.post1.dist-info/METADATA
veriphi_core-0.1.3.post1.dist-info/WHEEL
veriphi_core-0.1.3.post1.dist-info/licenses/LICENSE
veriphi_core/__init__.py
veriphi_core/interface.py
veriphi_core/utils.py
veriphi_core/veriphi_core_py.abi3.so
veriphi_core-0.1.3.post1.dist-info/RECORD
