Metadata-Version: 2.4
Name: veriphi_core
Version: 0.1.3.post1
Classifier: Programming Language :: Python :: 3
Classifier: Programming Language :: Rust
Classifier: License :: OSI Approved :: GNU Affero General Public License v3
Classifier: Operating System :: OS Independent
Requires-Dist: numpy>=1.26.4,<2.0 ; python_full_version < '3.11'
Requires-Dist: numpy>=2.3.0,<2.4 ; python_full_version >= '3.11'
Requires-Dist: pycryptodome==3.23.0
Requires-Dist: pytest==8.4.1 ; extra == 'dev'
Provides-Extra: dev
License-File: LICENSE
Summary: Python bindings for veriphi-core routines
Author: Veriphi Labs LTD
License-Expression: AGPL-3.0
Requires-Python: >=3.10
